osometweet/__init__.py
osometweet/api.py
osometweet/expansions.py
osometweet/fields.py
osometweet/oauth.py
osometweet/rate_limit_manager.py
osometweet/utils.py
osometweet/wrangle.py
osometweet-0.4.dist-info/LICENSE
osometweet-0.4.dist-info/METADATA
osometweet-0.4.dist-info/WHEEL
osometweet-0.4.dist-info/top_level.txt
osometweet-0.4.dist-info/RECORD
