Metadata-Version: 2.1
Name: osometweet
Version: 0.4
Summary: OSoMe Twitter library for academic researchers
Home-page: https://github.com/truthy/osometweet
Author: Matthew DeVerna, Christopher Torres-Lugo, Kaicheng Yang
Author-email: mdeverna@iu.edu, torresch@indiana.edu, yangkc@iu.edu
License: MIT
Download-URL: https://pypi.org/project/osometweet/
Project-URL: Documentation, https://github.com/truthy/osometweet
Project-URL: Issue Tracker, https://github.com/truthy/osometweet/issues
Project-URL: Source Code, https://github.com/truthy/osometweet
Platform: UNKNOWN
Requires-Python: >=3.5
License-File: LICENSE
Requires-Dist: requests (>=2.24.0)
Requires-Dist: requests-oauthlib (>=1.3.0)
